piot
