Metadata-Version: 2.1
Name: piot
Version: 0.0.2
Summary: Load and run device drivers at specific intervals, mainly sensor reading
Home-page: https://github.com/frantp/piot
Author: Francisco Troncoso Pastoriza
Author-email: frantp90@gmail.com
License: UNKNOWN
Keywords: driver sensor reading
Platform: UNKNOWN
Classifier: Programming Language :: Python :: 3
Classifier: License :: OSI Approved :: Apache Software License
Classifier: Operating System :: OS Independent
Requires-Python: >=3.5
